{
  "id": "driver-automation-tool",
  "name": "Driver Automation Tool",
  "description": "Driver Automation Tool is a PowerShell WPF desktop app that automates the full lifecycle of OEM driver and BIOS package management for ConfigMgr and Intune. It automatically discovers vendor catalogs, downloads with resume-enabled curl, extracts, builds WIMs, and wraps packages as .intunewin for Intune Win32 deployment. The tool supports multiple OEMs, BIOS update handling, hash verification, and configurable packaging (DISM/wimlib/7-Zip) to streamline ConfigMgr and Intune workflows.",
  "keywords": [
    "intune",
    "configmgr",
    "oem-drivers",
    "bios-updates",
    "wim-packaging",
    "dism",
    "wimlib",
    "7zip"
  ],
  "author": "Maurice Daly",
  "authorPicture": "https://github.com/maurice-daly.png",
  "githubUrl": "https://github.com/maurice-daly",
  "linkedinUrl": "https://www.linkedin.com/in/mauricedaly/",
  "xUrl": "https://x.com/modaly_it",
  "repoUrl": "https://github.com/maurice-daly/DriverAutomationTool",
  "downloadUrl": "https://github.com/maurice-daly/DriverAutomationTool/archive/refs/heads/master.zip",
  "websiteUrl": "https://www.driverautomationtool.com/",
  "category": "packaging",
  "type": "other",
  "dateAdded": "2026-05-10",
  "securityCheck": {
    "passed": 6,
    "total": 6,
    "filesScanned": 33,
    "lastChecked": "2026-07-12",
    "forceApproved": false,
    "status": "passed",
    "aiSummary": "No security issues detected. Code appears safe for an Intune management tool.",
    "checks": {
      "noObfuscatedCode": {
        "passed": true
      },
      "noRemoteExecution": {
        "passed": true
      },
      "noCredentialTheft": {
        "passed": true
      },
      "noDataExfiltration": {
        "passed": true
      },
      "noMaliciousPatterns": {
        "passed": true
      },
      "noHardcodedSecrets": {
        "passed": true
      }
    },
    "notes": []
  },
  "repoStats": {
    "stars": 549,
    "forks": 137,
    "license": "NOASSERTION",
    "lastUpdated": "2026-06-25T14:31:28Z",
    "archived": false
  },
  "authors": [
    {
      "name": "Maurice Daly",
      "githubUrl": "https://github.com/maurice-daly",
      "picture": "https://github.com/maurice-daly.png",
      "linkedinUrl": "https://www.linkedin.com/in/mauricedaly/",
      "xUrl": "https://x.com/modaly_it"
    }
  ],
  "screenshots": [
    "screenshots/driver-automation-tool/screenshot-1.png",
    "screenshots/driver-automation-tool/screenshot-2.png",
    "screenshots/driver-automation-tool/screenshot-3.png",
    "screenshots/driver-automation-tool/screenshot-4.png",
    "screenshots/driver-automation-tool/screenshot-5.png"
  ]
}
